nypl_py_utils/__init__.py
nypl_py_utils/classes/avro_client.py
nypl_py_utils/classes/cloudlibrary_client.py
nypl_py_utils/classes/kinesis_client.py
nypl_py_utils/classes/kms_client.py
nypl_py_utils/classes/mysql_client.py
nypl_py_utils/classes/oauth2_api_client.py
nypl_py_utils/classes/postgresql_client.py
nypl_py_utils/classes/redshift_client.py
nypl_py_utils/classes/s3_client.py
nypl_py_utils/classes/secrets_manager_client.py
nypl_py_utils/classes/sftp_client.py
nypl_py_utils/functions/config_helper.py
nypl_py_utils/functions/log_helper.py
nypl_py_utils/functions/obfuscation_helper.py
nypl_py_utils/functions/patron_data_helper.py
nypl_py_utils/functions/research_catalog_identifier_helper.py
nypl_py_utils-1.8.0.dist-info/METADATA
nypl_py_utils-1.8.0.dist-info/WHEEL
nypl_py_utils-1.8.0.dist-info/licenses/LICENSE
nypl_py_utils-1.8.0.dist-info/RECORD
