Metadata-Version: 2.4
Name: nypl_py_utils
Version: 1.8.0
Summary: A package containing Python utilities for use across NYPL
Project-URL: Homepage, https://github.com/NYPL/python-utils
Project-URL: Bug Tracker, https://github.com/NYPL/python-utils/issues
Author-email: Aaron Friedman <aaronfriedman@nypl.org>
License-File: LICENSE
Classifier: License :: OSI Approved :: MIT License
Classifier: Operating System :: OS Independent
Classifier: Programming Language :: Python :: 3
Requires-Python: >=3.9
Provides-Extra: avro-client
Requires-Dist: fastavro>=1.11.1; extra == 'avro-client'
Requires-Dist: requests>=2.28.1; extra == 'avro-client'
Provides-Extra: cloudlibrary-client
Requires-Dist: requests>=2.28.1; extra == 'cloudlibrary-client'
Provides-Extra: config-helper
Requires-Dist: boto3>=1.26.5; extra == 'config-helper'
Requires-Dist: botocore>=1.29.5; extra == 'config-helper'
Requires-Dist: pyyaml>=6.0; extra == 'config-helper'
Provides-Extra: development
Requires-Dist: bcrypt>=4.0.1; extra == 'development'
Requires-Dist: boto3>=1.26.5; extra == 'development'
Requires-Dist: botocore>=1.29.5; extra == 'development'
Requires-Dist: fastavro>=1.11.1; extra == 'development'
Requires-Dist: flake8>=6.0.0; extra == 'development'
Requires-Dist: freezegun>=1.2.2; extra == 'development'
Requires-Dist: mock>=4.0.3; extra == 'development'
Requires-Dist: mysql-connector-python>=8.0.32; extra == 'development'
Requires-Dist: oauthlib>=3.2.2; extra == 'development'
Requires-Dist: pandas>=2.2.2; extra == 'development'
Requires-Dist: paramiko>=3.4.1; extra == 'development'
Requires-Dist: psycopg[binary]>=3.1.6; extra == 'development'
Requires-Dist: pytest-mock>=3.10.0; extra == 'development'
Requires-Dist: pytest==8.0; extra == 'development'
Requires-Dist: pyyaml>=6.0; extra == 'development'
Requires-Dist: redshift-connector>=2.0.909; extra == 'development'
Requires-Dist: requests-mock>=1.10.0; extra == 'development'
Requires-Dist: requests-oauthlib>=1.3.1; extra == 'development'
Requires-Dist: requests>=2.28.1; extra == 'development'
Requires-Dist: structlog>=25.4.0; extra == 'development'
Provides-Extra: kinesis-client
Requires-Dist: boto3>=1.26.5; extra == 'kinesis-client'
Requires-Dist: botocore>=1.29.5; extra == 'kinesis-client'
Provides-Extra: kms-client
Requires-Dist: boto3>=1.26.5; extra == 'kms-client'
Requires-Dist: botocore>=1.29.5; extra == 'kms-client'
Provides-Extra: log-helper
Requires-Dist: structlog>=25.4.0; extra == 'log-helper'
Provides-Extra: mysql-client
Requires-Dist: mysql-connector-python>=8.0.32; extra == 'mysql-client'
Provides-Extra: oauth2-api-client
Requires-Dist: oauthlib>=3.2.2; extra == 'oauth2-api-client'
Requires-Dist: requests-oauthlib>=1.3.1; extra == 'oauth2-api-client'
Provides-Extra: obfuscation-helper
Requires-Dist: bcrypt>=4.0.1; extra == 'obfuscation-helper'
Provides-Extra: patron-data-helper
Requires-Dist: botocore>=1.29.5; extra == 'patron-data-helper'
Requires-Dist: pandas>=2.2.2; extra == 'patron-data-helper'
Requires-Dist: psycopg[binary]>=3.1.6; extra == 'patron-data-helper'
Requires-Dist: redshift-connector>=2.0.909; extra == 'patron-data-helper'
Provides-Extra: postgresql-client
Requires-Dist: psycopg[binary]>=3.1.6; extra == 'postgresql-client'
Provides-Extra: redshift-client
Requires-Dist: botocore>=1.29.5; extra == 'redshift-client'
Requires-Dist: redshift-connector>=2.0.909; extra == 'redshift-client'
Provides-Extra: research-catalog-identifier-helper
Requires-Dist: requests>=2.28.1; extra == 'research-catalog-identifier-helper'
Provides-Extra: s3-client
Requires-Dist: boto3>=1.26.5; extra == 's3-client'
Requires-Dist: botocore>=1.29.5; extra == 's3-client'
Provides-Extra: secrets-manager-client
Requires-Dist: boto3>=1.26.5; extra == 'secrets-manager-client'
Requires-Dist: botocore>=1.29.5; extra == 'secrets-manager-client'
Provides-Extra: sftp-client
Requires-Dist: paramiko>=3.4.1; extra == 'sftp-client'
